{
    "intents":[
        {"tag": "greetings",
        "patterns": ["hello","hi","greetings","hey have a good day","what's up"],
        "responses":["Hello!","Hi!","What can i do for you?"],
        "context": [""]},
        {"tag": "off",
        "patterns": ["goodbye","bye","see you later","thank you","rest","now you can stop","shut down","stop"],
        "responses":["See you later!","Have a good day!","Goodbye!","Bye! See you again later!"],
        "context": [""]},
        {"tag": "thanks",
         "patterns": ["Thanks", "Thank you", "That's helpful", "Awesome, thanks", "Thanks for helping me"],
         "responses": ["My pleasure", "You're Welcome"],
         "context": [""]},
        {"tag": "introduce",
        "patterns":["Who are you","Introduce yourself","What's your name","Where are you from?"],
        "responses":["I am an AI chatbot. I was developed by Nguyen Viet Trung from NEU, IT63B"],
        "context": [""]},
        {"tag":"menu",
        "patterns":["Solve equation","Open Math Menu","Giai phuong trinh","Mo menu giai toan","Giai toan"],
        "responses":["Chọn 1 trong các lựa chọn sau để tiếp tục: \n1: Giải phương trình bậc nhất \n2: Giải phương trình bậc hai\n 3:Giải phương trình bậc 3\nStop: Dừng ở trong menu"],
        "context":[""]},
        {"tag":"math1",
        "patterns":["1","one","bac 1","bac nhat","Giai phuong trinh bac nhat"],
        "responses":["Phương trình bậc nhất có dạng aX + b = 0\n Nhập giá trị a: **\n Nhập giá trị b:"],
        "context":["input_a","input_b","response"]},
        {"tag":"math2",
        "patterns":["2","two","bac 2","bac hai","Giai phuong trinh bac hai"],
        "responses":["Phương trình bậc nhất có dạng aX^2 + bX + c = 0\n Nhập giá trị a: **\n Nhập giá trị b: **\n Nhập giá trị c:"],
        "context":[""]},
        {"tag":"math3",
        "patterns":["3","three","bac 3","bac ba","Giai phuong trinh bac ba"],
        "responses":["Phương trình bậc nhất có dạng aX^3 + bX^2 + cX+ d = 0\n Nhập giá trị a: **\n Nhập giá trị b: **\n Nhập giá trị c: **\n Nhập giá trị d: "],
        "context":[""]},
        {"tag":"joke",
        "patterns":["Tell me a joke","Tell me something funny","Say something funny","Show me your sense of humor","Proof that you are a comedian"],
        "responses":["Did you know, if you get pregnant in the Amazon, it's next day delivery","Giao diện của bạn trông mới mẻ đấy, mới cài lại win hả?","Tham gia giao thông như điền vào chỗ trống vậy, thiếu đâu mình đi vô đó!","Cầm tiền thì sợ tiền rơi, cầm tờ A4 đời đời ấm no"],
        "context":[]},
        {"tag":"weather",
        "patterns":["What's the weather like?", "Tell me the weather forecast", "Is it going to rain today?", "Weather update", "Weather"],
        "responses":["I don't have real-time news updates. Maybe sunny","I don't have real-time news updates. Maybe rainy","I don't have real-time news updates.Maybe humid","I don't have real-time news updates. Maybe mild"],
        "context":[]},
        {"tag":"AI",
        "patterns":["AI là gì","What is AI","AI definition","Definition of AI?","Introduce AI","AI viết tắt"],
        "responses":["AI la Artifical Intelligence","AI is Artifical Intelligence","AI là trí thông minh được thể hiện bằng máy móc"],
        "context":[]},
        {"tag":"API",
        "patterns":["What is API", "API definition","API là gì","Definition of API?","Chức năng API?","Introduce API","API viết tắt"],
        "responses":["API là viết tắt của Application Programming Interface (Giao diện Lập trình Ứng dụng)","Đây là một tập hợp các quy tắc và công cụ cho phép các phần mềm ứng dụng giao tiếp và tương tác với nhau. API giúp các ứng dụng khác nhau chia sẻ dữ liệu và chức năng mà không cần biết cách chúng được triển khai bên trong.",
        "API có thể thực hiện nhiều nhiệm vụ khác nhau, bao gồm truyền dữ liệu giữa các ứng dụng, cho phép ứng dụng sử dụng chức năng của một ứng dụng khác mà không cần biết chi tiết cài đặt bên trong, hoặc thậm chí cung cấp cách cho phép các nhóm phần mềm khác nhau làm việc cùng nhau."],
        "context":[]},
        {"tag":"NEU",
        "patterns":["NEU viết tắt cho gì","What is NEU","Introduce NEU"],
        "responses":["NEU is National Economy University","NEU là Đại học kinh tế quốc dân"],
        "context":[]},
        {"tag":"Optimizing (tối ưu hóa ) definition",
        "patterns":["What is Optimizing","Optimizing là gì","Optimizing","Giới thiệu Optimizing","Tối ưu hóa là gì"],
        "responses":["Là việc giải quyết các bài toán quy hoạch toán học","Là giải quyết các bài toán tìm cực trị, tìm phương án tối ưu hoặc cận tối ưu (các bài toán Heuristic)"],
        "context":[]}
    ]
}